testmjarczewski/__init__.py
testmjarczewski/m_mod_mjarczewski.py
testmjarczewski-0.0.1.dist-info/LICENSE.txt
testmjarczewski-0.0.1.dist-info/METADATA
testmjarczewski-0.0.1.dist-info/WHEEL
testmjarczewski-0.0.1.dist-info/top_level.txt
testmjarczewski-0.0.1.dist-info/RECORD
