Metadata-Version: 2.1
Name: testmjarczewski
Version: 0.0.1
Summary: My test package
Author-email: MJ <marek.jarczewski81@gmail.com>
License: MIT License
Keywords: testmjarczewski,name,surname,fun function
Classifier: Framework :: IDLE
Classifier: Natural Language :: Polish
Requires-Python: >=3.0
License-File: LICENSE.txt
Requires-Dist: python-version (>='3.0')
Requires-Dist: numpy
